pywaybackup/Arguments.py
pywaybackup/Exception.py
pywaybackup/PyWayBackup.py
pywaybackup/Snapshot.py
pywaybackup/SnapshotCollection.py
pywaybackup/Verbosity.py
pywaybackup/Worker.py
pywaybackup/__init__.py
pywaybackup/archive_download.py
pywaybackup/archive_save.py
pywaybackup/db.py
pywaybackup/files.py
pywaybackup/helper.py
pywaybackup/main.py
pywaybackup-4.1.4.dist-info/LICENSE
pywaybackup-4.1.4.dist-info/METADATA
pywaybackup-4.1.4.dist-info/WHEEL
pywaybackup-4.1.4.dist-info/entry_points.txt
pywaybackup-4.1.4.dist-info/top_level.txt
pywaybackup-4.1.4.dist-info/RECORD
