Metadata-Version: 2.1
Name: pywaybackup
Version: 4.1.4
Summary: Query and download archive.org as simple as possible.
Author-email: bitdruid <bitdruid@outlook.com>
License: MIT License
Project-URL: homepage, https://github.com/bitdruid/python-wayback-machine-downloader
Requires-Python: >=3.8
License-File: LICENSE
Requires-Dist: ruff
Requires-Dist: SQLAlchemy==2.0.43
Requires-Dist: requests==2.32.3
Requires-Dist: tqdm==4.67.1
Requires-Dist: pylibmagic==0.5.0
Requires-Dist: python-magic==0.4.27; sys_platform == "linux"
Requires-Dist: python-magic-bin==0.4.14; sys_platform == "win32" or sys_platform == "darwin"
